LICENSE
drfexts/__init__.py
drfexts/authentication.py
drfexts/choices.py
drfexts/constants.py
drfexts/exceptions.py
drfexts/fields.py
drfexts/filtersets/__init__.py
drfexts/filtersets/backends.py
drfexts/filtersets/fields.py
drfexts/filtersets/filters.py
drfexts/filtersets/widgets.py
drfexts/middlewares.py
drfexts/models.py
drfexts/pagination.py
drfexts/paginators.py
drfexts/parsers.py
drfexts/permissions.py
drfexts/renderers.py
drfexts/routers.py
drfexts/serializers/__init__.py
drfexts/serializers/fields.py
drfexts/serializers/mixins.py
drfexts/serializers/serializers.py
drfexts/settings.py
drfexts/storages.py
drfexts/utils/__init__.py
drfexts/utils/encoders.py
drfexts/utils/log.py
drfexts/utils/string.py
drfexts/utils/utils.py
drfexts/viewsets.py
drfexts-3.13.5.dist-info/LICENSE
drfexts-3.13.5.dist-info/METADATA
drfexts-3.13.5.dist-info/WHEEL
drfexts-3.13.5.dist-info/RECORD
