Metadata-Version: 2.1
Name: drfexts
Version: 3.13.5
Summary: Django Restframework Utils
Home-page: https://github.com/aiden520/drfexts
License: Apache-2.0
Keywords: django,restframework
Author: aiden
Author-email: allaher@icloud.com
Requires-Python: >=3.10,<4.0.0
Classifier: License :: OSI Approved :: Apache Software License
Classifier: Programming Language :: Python :: 3
Classifier: Programming Language :: Python :: 3.10
Classifier: Programming Language :: Python :: 3.11
Classifier: Programming Language :: Python :: 3.12
Classifier: Programming Language :: Python :: 3.13
Requires-Dist: django (>=4.2)
Requires-Dist: django-currentuser (>=0.5.3)
Requires-Dist: django-filter (>=21.1)
Requires-Dist: django-storages (>=1.12.3)
Requires-Dist: djangorestframework (>=3.14.0)
Requires-Dist: djangorestframework-csv (>=2.1.1)
Requires-Dist: drf-flex-fields (>=0.9.8)
Requires-Dist: openpyxl (>=3.0.9)
Requires-Dist: orjson (>=3.10.6)
Requires-Dist: pip (>=21.3.1)
Requires-Dist: xlsxwriter (>=3.2.0)
Project-URL: Repository, https://github.com/aiden520/drfexts
